VizTyping/__init__.py
VizTyping/backend/__init__.py
VizTyping/backend/info.py
VizTyping/backend/status.py
VizTyping/backend/type.py
VizTyping/meta/__init__.py
VizTyping/meta/classifier_meta.py
VizTyping/meta/frame_meta.py
VizTyping/meta/label_info.py
VizTyping/meta/object_meta.py
VizTyping/request/__init__.py
VizTyping/request/add_infer_task.py
VizTyping/request/add_train_task.py
VizTyping/request/backend_register.py
VizTyping/request/rm_infer_task.py
VizTyping/request/rm_train_task.py
VizTyping/request/start_infer_model.py
VizTyping/request/stop_infer_model.py
backend/__init__.py
backend/info.py
backend/status.py
backend/type.py
meta/__init__.py
meta/classifier_meta.py
meta/frame_meta.py
meta/label_info.py
meta/object_meta.py
request/__init__.py
request/add_infer_task.py
request/add_train_task.py
request/backend_register.py
request/rm_infer_task.py
request/rm_train_task.py
request/start_infer_model.py
request/stop_infer_model.py
VizTyping-0.0.0.2.dist-info/LICENCE
VizTyping-0.0.0.2.dist-info/METADATA
VizTyping-0.0.0.2.dist-info/WHEEL
VizTyping-0.0.0.2.dist-info/top_level.txt
VizTyping-0.0.0.2.dist-info/RECORD
